TopsisAbhinav101903684/101903684.py
TopsisAbhinav101903684/__init__.py
Topsis_Abhinav_101903684-3.0.1.dist-info/METADATA
Topsis_Abhinav_101903684-3.0.1.dist-info/WHEEL
Topsis_Abhinav_101903684-3.0.1.dist-info/top_level.txt
Topsis_Abhinav_101903684-3.0.1.dist-info/RECORD
