Metadata-Version: 2.1
Name: Topsis-Abhinav-101903684
Version: 3.0.1
Summary: TOPSIS
Home-page: https://github.com/
Author: Abhinav Goyal
Author-email: agoyal2_be19@thapar.edu
License: MIT
Platform: UNKNOWN
Classifier: License :: OSI Approved :: MIT License
Classifier: Programming Language :: Python :: 3.6
Classifier: Programming Language :: Python :: 3.7
Classifier: Programming Language :: Python :: 3.8
